README.md
setup.py
bin/nirone
nirone/__init__.py
nirone/nirone.py
nirone.egg-info/PKG-INFO
nirone.egg-info/SOURCES.txt
nirone.egg-info/dependency_links.txt
nirone.egg-info/requires.txt
nirone.egg-info/top_level.txt