Metadata-Version: 2.1
Name: nirone
Version: 0.0.1
Summary: NIROne programming interface
Home-page: https://github.com/TristanLieberherr/NIROne_package
Author: Tristan Lieberherr
Author-email: tristan.lieberherr@heig-vd.ch
License: UNKNOWN
Platform: UNKNOWN
Classifier: Development Status :: 4 - Beta
Classifier: Intended Audience :: Developers
Classifier: Programming Language :: Python :: 3
Classifier: License :: OSI Approved :: MIT License
Classifier: Operating System :: OS Independent
